LICENSE
README.md
setup.py
citrixnetscalermemoryleak/__init__.py
citrixnetscalermemoryleak/main.py
citrixnetscalermemoryleak.egg-info/PKG-INFO
citrixnetscalermemoryleak.egg-info/SOURCES.txt
citrixnetscalermemoryleak.egg-info/dependency_links.txt
citrixnetscalermemoryleak.egg-info/entry_points.txt
citrixnetscalermemoryleak.egg-info/requires.txt
citrixnetscalermemoryleak.egg-info/top_level.txt
citrixnetscalermemoryleak/includes/__init__.py
citrixnetscalermemoryleak/includes/bot.py
citrixnetscalermemoryleak/includes/filereader.py
citrixnetscalermemoryleak/includes/scan.py
citrixnetscalermemoryleak/includes/writefile.py
citrixnetscalermemoryleak/utils/__init__.py
citrixnetscalermemoryleak/utils/configure.py
citrixnetscalermemoryleak/utils/const.py
citrixnetscalermemoryleak/utils/helpers.py
citrixnetscalermemoryleak/utils/status.py